odoo8_addon_product_unique_serial-8.0.1.0.3-nspkg.pth
odoo_addons/product_unique_serial/README.rst
odoo_addons/product_unique_serial/__init__.py
odoo_addons/product_unique_serial/__openerp__.py
odoo_addons/product_unique_serial/demo/product_product.xml
odoo_addons/product_unique_serial/demo/stock_production_lot.xml
odoo_addons/product_unique_serial/i18n/ca.po
odoo_addons/product_unique_serial/i18n/de.po
odoo_addons/product_unique_serial/i18n/es.po
odoo_addons/product_unique_serial/i18n/es_AR.po
odoo_addons/product_unique_serial/i18n/es_MX.po
odoo_addons/product_unique_serial/i18n/fi.po
odoo_addons/product_unique_serial/i18n/fr.po
odoo_addons/product_unique_serial/i18n/fr_CH.po
odoo_addons/product_unique_serial/i18n/hr.po
odoo_addons/product_unique_serial/i18n/hr_HR.po
odoo_addons/product_unique_serial/i18n/it.po
odoo_addons/product_unique_serial/i18n/product_unique_serial.pot
odoo_addons/product_unique_serial/i18n/pt.po
odoo_addons/product_unique_serial/i18n/pt_BR.po
odoo_addons/product_unique_serial/i18n/ro.po
odoo_addons/product_unique_serial/i18n/sl.po
odoo_addons/product_unique_serial/i18n/tr.po
odoo_addons/product_unique_serial/i18n/tr_TR.po
odoo_addons/product_unique_serial/i18n/vi_VN.po
odoo_addons/product_unique_serial/i18n/zh_CN.po
odoo_addons/product_unique_serial/models/__init__.py
odoo_addons/product_unique_serial/models/product_template.py
odoo_addons/product_unique_serial/models/stock_move.py
odoo_addons/product_unique_serial/models/stock_production_lot.py
odoo_addons/product_unique_serial/static/description/icon.png
odoo_addons/product_unique_serial/tests/__init__.py
odoo_addons/product_unique_serial/tests/test_for_unicity.py
odoo_addons/product_unique_serial/views/product_template.xml
odoo_addons/product_unique_serial/views/stock_production_lot.xml
odoo_addons/product_unique_serial/wizards/__init__.py
odoo_addons/product_unique_serial/wizards/stock_transfer_details.py
odoo8_addon_product_unique_serial-8.0.1.0.3.dist-info/METADATA
odoo8_addon_product_unique_serial-8.0.1.0.3.dist-info/WHEEL
odoo8_addon_product_unique_serial-8.0.1.0.3.dist-info/namespace_packages.txt
odoo8_addon_product_unique_serial-8.0.1.0.3.dist-info/top_level.txt
odoo8_addon_product_unique_serial-8.0.1.0.3.dist-info/RECORD
